README.md
setup.py
boltobs_greenfield.egg-info/PKG-INFO
boltobs_greenfield.egg-info/SOURCES.txt
boltobs_greenfield.egg-info/dependency_links.txt
boltobs_greenfield.egg-info/requires.txt
boltobs_greenfield.egg-info/top_level.txt
swagger_client/__init__.py
swagger_client/api_client.py
swagger_client/configuration.py
swagger_client/rest.py
swagger_client/api/__init__.py
swagger_client/api/api_keys_api.py
swagger_client/api/apps_api.py
swagger_client/api/authorization_api.py
swagger_client/api/custodians_api.py
swagger_client/api/health_api.py
swagger_client/api/invoices_api.py
swagger_client/api/lightning__internal_node_api.py
swagger_client/api/lightning__store_api.py
swagger_client/api/miscelleneous_api.py
swagger_client/api/notifications__current_user_api.py
swagger_client/api/payment_requests_api.py
swagger_client/api/payout_processors_api.py
swagger_client/api/pull_payments__management_api.py
swagger_client/api/pull_payments__public_api.py
swagger_client/api/pull_payments_payout__public_api.py
swagger_client/api/server_info_api.py
swagger_client/api/store_payment_methods__lightning_network_api.py
swagger_client/api/store_payment_methods__lnurl_pay_api.py
swagger_client/api/store_payment_methods__on_chain_api.py
swagger_client/api/store_payment_methods_api.py
swagger_client/api/store_wallet__on_chain_api.py
swagger_client/api/stores__email_api.py
swagger_client/api/stores__payout_processors_api.py
swagger_client/api/stores__payouts_api.py
swagger_client/api/stores__users_api.py
swagger_client/api/stores_api.py
swagger_client/api/users_api.py
swagger_client/api/webhooks_api.py
swagger_client/models/__init__.py
swagger_client/models/add_customer_email_request.py
swagger_client/models/all_of_application_user_data_created.py
swagger_client/models/all_of_checkout_options_expiration_minutes.py
swagger_client/models/all_of_checkout_options_monitoring_minutes.py
swagger_client/models/all_of_create_lightning_invoice_request_expiry.py
swagger_client/models/all_of_lightning_automated_transfer_settings_interval_seconds.py
swagger_client/models/all_of_lightning_invoice_data_expires_at.py
swagger_client/models/all_of_lightning_invoice_data_paid_at.py
